phylodeep_data_BDSS_large/__init__.py
phylodeep_data_BDSS_large/ci_computation/predicted_values/BDSS_LARGE_CNN.csv.gz
phylodeep_data_BDSS_large/ci_computation/predicted_values/BDSS_LARGE_FFNN.csv.gz
phylodeep_data_BDSS_large/ci_computation/target_values/BDSS_LARGE.csv.gz
phylodeep_data_BDSS_large-0.0.1.dist-info/METADATA
phylodeep_data_BDSS_large-0.0.1.dist-info/WHEEL
phylodeep_data_BDSS_large-0.0.1.dist-info/top_level.txt
phylodeep_data_BDSS_large-0.0.1.dist-info/RECORD
